{"name":"PPT","postlist":[{"title":"「Python」PPT 转 Markdown","slug":"技术/python/「Python」PPT 转 Markdown","date":"2022-10-21T09:11:21.000Z","updated":"2022-12-25T14:31:13.060Z","comments":true,"path":"api/articles/技术/python/「Python」PPT 转 Markdown.json","excerpt":null,"keywords":null,"cover":null,"content":null,"raw":null,"categories":[{"name":"技术","path":"api/categories/技术.json"},{"name":"Python","path":"api/categories/Python.json"}],"tags":[{"name":"技术","path":"api/tags/技术.json"},{"name":"Python","path":"api/tags/Python.json"},{"name":"PPT","path":"api/tags/PPT.json"}]}]}